poetry_example/__init__.py
poetry_example-1.0.0.dist-info/WHEEL
poetry_example-1.0.0.dist-info/METADATA
poetry_example-1.0.0.dist-info/RECORD
