Metadata-Version: 2.1
Name: poetry-example
Version: 1.0.0
Summary: 
Author: Sebastian Plamauer
Author-email: sebastian.plamauer@motius.de
Requires-Python: >=3.7,<4.0
Classifier: Programming Language :: Python :: 3
Classifier: Programming Language :: Python :: 3.7
Classifier: Programming Language :: Python :: 3.8
Requires-Dist: requests (>=2.24.0,<3.0.0)
